<?xml version="1.0" encoding="UTF-8" standalone="yes"?>
<Attack>
    <IPDescriptor>
        <IPAddress>219.146.12.180</IPAddress>
        <LocationDescriptor>
            <CountryName>China</CountryName>
            <CountryCode>CN</CountryCode>
            <RegionName>Shandong Sheng</RegionName>
            <RegionCode>37</RegionCode>
            <City>Jinan</City>
            <ZipCode></ZipCode>
            <TimeZone>Asia/Shanghai</TimeZone>
            <Latitude>36.6683</Latitude>
            <Longitude>116.9972</Longitude>
            <MetroCode>0</MetroCode>
        </LocationDescriptor>
        <BlacklistingDescriptor>
            <BlacklistingLevel>5</BlacklistingLevel>
        </BlacklistingDescriptor>
        <AdversaryHostDescriptor>
            <NetworkRange>219.0.0.0 - 219.255.255.255</NetworkRange>
            <NetworkSize>16777215</NetworkSize>
            <NetworkName>IPv4 address block not managed by the RIPE NCC</NetworkName>
        </AdversaryHostDescriptor>
        <AdversarySystemDescriptor>
            <PortsDescriptor amount="0"/>
        </AdversarySystemDescriptor>
        <ReverseIPDescriptor AmountOfVirtualHosts="0"/>
    </IPDescriptor>
    <DateDescriptor>
        <Fulldate>2015-10-11</Fulldate>
        <Year>2015</Year>
        <Month>10</Month>
        <Day>11</Day>
        <Time>07:57:11</Time>
    </DateDescriptor>
</Attack>
