<?xml version="1.0" encoding="UTF-8" standalone="yes"?>
<Attack>
    <IPDescriptor>
        <IPAddress>173.203.211.32</IPAddress>
        <LocationDescriptor>
            <CountryName>United States</CountryName>
            <CountryCode>US</CountryCode>
            <RegionName>Texas</RegionName>
            <RegionCode>TX</RegionCode>
            <City>San Antonio</City>
            <ZipCode>78218</ZipCode>
            <TimeZone>America/Chicago</TimeZone>
            <Latitude>29.4889</Latitude>
            <Longitude>-98.3987</Longitude>
            <MetroCode>641</MetroCode>
        </LocationDescriptor>
        <BlacklistingDescriptor>
            <BlacklistingLevel>0</BlacklistingLevel>
        </BlacklistingDescriptor>
        <AdversaryHostDescriptor>
            <NetworkRange>173.0.0.0 - 173.255.255.255</NetworkRange>
            <NetworkSize>16777215</NetworkSize>
            <NetworkName>IPv4 address block not managed by the RIPE NCC</NetworkName>
        </AdversaryHostDescriptor>
        <AdversarySystemDescriptor>
            <OSDescriptor>HP P2000 G3 NAS device</OSDescriptor>
            <PortsDescriptor amount="4">
                <PortDescriptor>
                    <ProgramName>ftp</ProgramName>
                    <Port>21</Port>
                </PortDescriptor>
                <PortDescriptor>
                    <ProgramName>ssh</ProgramName>
                    <Port>22</Port>
                </PortDescriptor>
                <PortDescriptor>
                    <ProgramName>http</ProgramName>
                    <Port>80</Port>
                </PortDescriptor>
                <PortDescriptor>
                    <ProgramName>https</ProgramName>
                    <Port>443</Port>
                </PortDescriptor>
            </PortsDescriptor>
        </AdversarySystemDescriptor>
        <ReverseIPDescriptor AmountOfVirtualHosts="28">
            <VirtualHost>
                <VirtualHostname>acceptcard.ru</VirtualHostname>
            </VirtualHost>
            <VirtualHost>
                <VirtualHostname>acceptcards.ru</VirtualHostname>
            </VirtualHost>
            <VirtualHost>
                <VirtualHostname>blog.rbkmoney.ru</VirtualHostname>
            </VirtualHost>
            <VirtualHost>
                <VirtualHostname>fsg.rbkmoney.ru</VirtualHostname>
            </VirtualHost>
            <VirtualHost>
                <VirtualHostname>give.rbkmoney.ru</VirtualHostname>
            </VirtualHost>
            <VirtualHost>
                <VirtualHostname>inplat.rbkmoney.ru</VirtualHostname>
            </VirtualHost>
            <VirtualHost>
                <VirtualHostname>leto.rbkmoney.ru</VirtualHostname>
            </VirtualHost>
            <VirtualHost>
                <VirtualHostname>mail1.rbkmoney.ru</VirtualHostname>
            </VirtualHost>
            <VirtualHost>
                <VirtualHostname>mail2.rbkmoney.ru</VirtualHostname>
            </VirtualHost>
            <VirtualHost>
                <VirtualHostname>mail3.rbkmoney.ru</VirtualHostname>
            </VirtualHost>
            <VirtualHost>
                <VirtualHostname>payment.rbkmoney.ru</VirtualHostname>
            </VirtualHost>
            <VirtualHost>
                <VirtualHostname>podarki.rbkmoney.ru</VirtualHostname>
            </VirtualHost>
            <VirtualHost>
                <VirtualHostname>raiffeisen.rbkmoney.ru</VirtualHostname>
            </VirtualHost>
            <VirtualHost>
                <VirtualHostname>rbcmoney.ru</VirtualHostname>
            </VirtualHost>
            <VirtualHost>
                <VirtualHostname>rbkcard.ru</VirtualHostname>
            </VirtualHost>
            <VirtualHost>
                <VirtualHostname>rbkmoney.com</VirtualHostname>
            </VirtualHost>
            <VirtualHost>
                <VirtualHostname>rbkmoney.net</VirtualHostname>
            </VirtualHost>
            <VirtualHost>
                <VirtualHostname>rbkmoney.org</VirtualHostname>
            </VirtualHost>
            <VirtualHost>
                <VirtualHostname>rbk.travel</VirtualHostname>
            </VirtualHost>
            <VirtualHost>
                <VirtualHostname>rupay.com</VirtualHostname>
            </VirtualHost>
            <VirtualHost>
                <VirtualHostname>rupay.ru</VirtualHostname>
            </VirtualHost>
            <VirtualHost>
                <VirtualHostname>smarttransferltd.com</VirtualHostname>
            </VirtualHost>
            <VirtualHost>
                <VirtualHostname>v-pos.ru</VirtualHostname>
            </VirtualHost>
            <VirtualHost>
                <VirtualHostname>www.give.rbkmoney.ru</VirtualHostname>
            </VirtualHost>
            <VirtualHost>
                <VirtualHostname>www.rbkmoney.com</VirtualHostname>
            </VirtualHost>
            <VirtualHost>
                <VirtualHostname>www.rbkmoney.ru</VirtualHostname>
            </VirtualHost>
            <VirtualHost>
                <VirtualHostname>www.rupay.com</VirtualHostname>
            </VirtualHost>
            <VirtualHost>
                <VirtualHostname>www.rupay.ru</VirtualHostname>
            </VirtualHost>
        </ReverseIPDescriptor>
    </IPDescriptor>
    <DateDescriptor>
        <Fulldate>2015-09-11</Fulldate>
        <Year>2015</Year>
        <Month>09</Month>
        <Day>11</Day>
        <Time>12:19:05</Time>
    </DateDescriptor>
</Attack>
