<?xml version="1.0" encoding="UTF-8" standalone="yes"?>
<Attack>
    <IPDescriptor>
        <IPAddress>218.94.117.236</IPAddress>
        <LocationDescriptor>
            <CountryName>China</CountryName>
            <CountryCode>CN</CountryCode>
            <RegionName>Jiangsu Sheng</RegionName>
            <RegionCode>32</RegionCode>
            <City>Nanjing</City>
            <ZipCode></ZipCode>
            <TimeZone>Asia/Shanghai</TimeZone>
            <Latitude>32.0617</Latitude>
            <Longitude>118.7778</Longitude>
            <MetroCode>0</MetroCode>
        </LocationDescriptor>
        <BlacklistingDescriptor>
            <BlacklistingLevel>0</BlacklistingLevel>
        </BlacklistingDescriptor>
        <AdversaryHostDescriptor>
            <NetworkRange>218.0.0.0 - 218.255.255.255</NetworkRange>
            <NetworkSize>16777215</NetworkSize>
            <NetworkName>IPv4 address block not managed by the RIPE NCC</NetworkName>
        </AdversaryHostDescriptor>
        <AdversarySystemDescriptor>
            <OSDescriptor>Microsoft Windows 7 Ultimate</OSDescriptor>
            <PortsDescriptor amount="32">
                <PortDescriptor>
                    <ProgramName>smtp</ProgramName>
                    <Port>25</Port>
                </PortDescriptor>
                <PortDescriptor>
                    <ProgramName>https</ProgramName>
                    <Port>443</Port>
                </PortDescriptor>
                <PortDescriptor>
                    <ProgramName>unknown</ProgramName>
                    <Port>880</Port>
                </PortDescriptor>
                <PortDescriptor>
                    <ProgramName>pop3s</ProgramName>
                    <Port>995</Port>
                </PortDescriptor>
                <PortDescriptor>
                    <ProgramName>garcon</ProgramName>
                    <Port>999</Port>
                </PortDescriptor>
                <PortDescriptor>
                    <ProgramName>unknown</ProgramName>
                    <Port>1001</Port>
                </PortDescriptor>
                <PortDescriptor>
                    <ProgramName>windows-icfw</ProgramName>
                    <Port>1002</Port>
                </PortDescriptor>
                <PortDescriptor>
                    <ProgramName>unknown</ProgramName>
                    <Port>1007</Port>
                </PortDescriptor>
                <PortDescriptor>
                    <ProgramName>pptp</ProgramName>
                    <Port>1723</Port>
                </PortDescriptor>
                <PortDescriptor>
                    <ProgramName>igrs</ProgramName>
                    <Port>3880</Port>
                </PortDescriptor>
                <PortDescriptor>
                    <ProgramName>irc</ProgramName>
                    <Port>6669</Port>
                </PortDescriptor>
                <PortDescriptor>
                    <ProgramName>tsa</ProgramName>
                    <Port>6689</Port>
                </PortDescriptor>
                <PortDescriptor>
                    <ProgramName>oracleas-https</ProgramName>
                    <Port>7443</Port>
                </PortDescriptor>
                <PortDescriptor>
                    <ProgramName>teradataordbms</ProgramName>
                    <Port>8002</Port>
                </PortDescriptor>
                <PortDescriptor>
                    <ProgramName>ftp-proxy</ProgramName>
                    <Port>8021</Port>
                </PortDescriptor>
                <PortDescriptor>
                    <ProgramName>unknown</ProgramName>
                    <Port>8045</Port>
                </PortDescriptor>
                <PortDescriptor>
                    <ProgramName>unknown</ProgramName>
                    <Port>8085</Port>
                </PortDescriptor>
                <PortDescriptor>
                    <ProgramName>unknown</ProgramName>
                    <Port>8180</Port>
                </PortDescriptor>
                <PortDescriptor>
                    <ProgramName>sophos</ProgramName>
                    <Port>8193</Port>
                </PortDescriptor>
                <PortDescriptor>
                    <ProgramName>sophos</ProgramName>
                    <Port>8194</Port>
                </PortDescriptor>
                <PortDescriptor>
                    <ProgramName>trivnet1</ProgramName>
                    <Port>8200</Port>
                </PortDescriptor>
                <PortDescriptor>
                    <ProgramName>unknown</ProgramName>
                    <Port>8290</Port>
                </PortDescriptor>
                <PortDescriptor>
                    <ProgramName>unknown</ProgramName>
                    <Port>8291</Port>
                </PortDescriptor>
                <PortDescriptor>
                    <ProgramName>tmi</ProgramName>
                    <Port>8300</Port>
                </PortDescriptor>
                <PortDescriptor>
                    <ProgramName>unknown</ProgramName>
                    <Port>8333</Port>
                </PortDescriptor>
                <PortDescriptor>
                    <ProgramName>m2mservices</ProgramName>
                    <Port>8383</Port>
                </PortDescriptor>
                <PortDescriptor>
                    <ProgramName>cvd</ProgramName>
                    <Port>8400</Port>
                </PortDescriptor>
                <PortDescriptor>
                    <ProgramName>abarsd</ProgramName>
                    <Port>8402</Port>
                </PortDescriptor>
                <PortDescriptor>
                    <ProgramName>https-alt</ProgramName>
                    <Port>8443</Port>
                </PortDescriptor>
                <PortDescriptor>
                    <ProgramName>sdr</ProgramName>
                    <Port>9010</Port>
                </PortDescriptor>
                <PortDescriptor>
                    <ProgramName>documentum</ProgramName>
                    <Port>10002</Port>
                </PortDescriptor>
                <PortDescriptor>
                    <ProgramName>unknown</ProgramName>
                    <Port>55555</Port>
                </PortDescriptor>
            </PortsDescriptor>
        </AdversarySystemDescriptor>
        <ReverseIPDescriptor AmountOfVirtualHosts="2">
            <VirtualHost>
                <VirtualHostname>miap.cc</VirtualHostname>
            </VirtualHost>
            <VirtualHost>
                <VirtualHostname>www.nj.fiberhome.com.cn</VirtualHostname>
            </VirtualHost>
        </ReverseIPDescriptor>
    </IPDescriptor>
    <DateDescriptor>
        <Fulldate>2015-04-29</Fulldate>
        <Year>2015</Year>
        <Month>04</Month>
        <Day>29</Day>
        <Time>18:28:51</Time>
    </DateDescriptor>
</Attack>
