<?xml version="1.0" encoding="UTF-8" standalone="yes"?>
<Attack>
    <IPDescriptor>
        <IPAddress>70.38.63.166</IPAddress>
        <LocationDescriptor>
            <CountryName>Canada</CountryName>
            <CountryCode>CA</CountryCode>
            <RegionName>Quebec</RegionName>
            <RegionCode>QC</RegionCode>
            <City>Montreal</City>
            <ZipCode>H3G</ZipCode>
            <TimeZone>America/Toronto</TimeZone>
            <Latitude>45.4987</Latitude>
            <Longitude>-73.5793</Longitude>
            <MetroCode>0</MetroCode>
        </LocationDescriptor>
        <BlacklistingDescriptor>
            <BlacklistingLevel>0</BlacklistingLevel>
        </BlacklistingDescriptor>
        <AdversaryHostDescriptor>
            <NetworkRange>70.0.0.0 - 70.255.255.255</NetworkRange>
            <NetworkSize>16777215</NetworkSize>
            <NetworkName>IPv4 address block not managed by the RIPE NCC</NetworkName>
        </AdversaryHostDescriptor>
        <AdversarySystemDescriptor>
            <OSDescriptor>OpenWrt Kamikaze 7.09 (Linux 2.6.22)</OSDescriptor>
            <PortsDescriptor amount="4">
                <PortDescriptor>
                    <ProgramName>ssh</ProgramName>
                    <Port>22</Port>
                </PortDescriptor>
                <PortDescriptor>
                    <ProgramName>dec-notes</ProgramName>
                    <Port>3333</Port>
                </PortDescriptor>
                <PortDescriptor>
                    <ProgramName>blackice-alerts</ProgramName>
                    <Port>8082</Port>
                </PortDescriptor>
                <PortDescriptor>
                    <ProgramName>unknown</ProgramName>
                    <Port>8085</Port>
                </PortDescriptor>
            </PortsDescriptor>
        </AdversarySystemDescriptor>
        <ReverseIPDescriptor AmountOfVirtualHosts="0"/>
    </IPDescriptor>
    <DateDescriptor>
        <Fulldate>2015-04-14</Fulldate>
        <Year>2015</Year>
        <Month>04</Month>
        <Day>14</Day>
        <Time>10:03:24</Time>
    </DateDescriptor>
</Attack>
