<?xml version="1.0" encoding="UTF-8" standalone="yes"?>
<Attack>
    <IPDescriptor>
        <IPAddress>93.174.93.239</IPAddress>
        <LocationDescriptor>
            <CountryName>Netherlands</CountryName>
            <CountryCode>NL</CountryCode>
            <RegionName></RegionName>
            <RegionCode></RegionCode>
            <City></City>
            <ZipCode></ZipCode>
            <TimeZone>Europe/Amsterdam</TimeZone>
            <Latitude>52.3667</Latitude>
            <Longitude>4.9</Longitude>
            <MetroCode>0</MetroCode>
        </LocationDescriptor>
        <BlacklistingDescriptor>
            <BlacklistingLevel>3</BlacklistingLevel>
        </BlacklistingDescriptor>
        <AdversaryHostDescriptor>
            <NetworkRange>93.174.93.0 - 93.174.93.255</NetworkRange>
            <NetworkSize>255</NetworkSize>
            <NetworkName>ECATEL LTD</NetworkName>
        </AdversaryHostDescriptor>
        <AdversarySystemDescriptor>
            <OSDescriptor>OpenWrt 12.09-rc1 Attitude Adjustment (Linux 3.3 - 3.7)</OSDescriptor>
            <PortsDescriptor amount="16">
                <PortDescriptor>
                    <ProgramName>ssh</ProgramName>
                    <Port>22</Port>
                </PortDescriptor>
                <PortDescriptor>
                    <ProgramName>http</ProgramName>
                    <Port>80</Port>
                </PortDescriptor>
                <PortDescriptor>
                    <ProgramName>unknown</ProgramName>
                    <Port>981</Port>
                </PortDescriptor>
                <PortDescriptor>
                    <ProgramName>imaps</ProgramName>
                    <Port>993</Port>
                </PortDescriptor>
                <PortDescriptor>
                    <ProgramName>surf</ProgramName>
                    <Port>1010</Port>
                </PortDescriptor>
                <PortDescriptor>
                    <ProgramName>netinfo</ProgramName>
                    <Port>1033</Port>
                </PortDescriptor>
                <PortDescriptor>
                    <ProgramName>ospfd</ProgramName>
                    <Port>2604</Port>
                </PortDescriptor>
                <PortDescriptor>
                    <ProgramName>neto-dcs</ProgramName>
                    <Port>3814</Port>
                </PortDescriptor>
                <PortDescriptor>
                    <ProgramName>edonkey</ProgramName>
                    <Port>4662</Port>
                </PortDescriptor>
                <PortDescriptor>
                    <ProgramName>upnp</ProgramName>
                    <Port>5000</Port>
                </PortDescriptor>
                <PortDescriptor>
                    <ProgramName>unknown</ProgramName>
                    <Port>5906</Port>
                </PortDescriptor>
                <PortDescriptor>
                    <ProgramName>clariion-evr01</ProgramName>
                    <Port>6389</Port>
                </PortDescriptor>
                <PortDescriptor>
                    <ProgramName>tsa</ProgramName>
                    <Port>6689</Port>
                </PortDescriptor>
                <PortDescriptor>
                    <ProgramName>afs3-kaserver</ProgramName>
                    <Port>7004</Port>
                </PortDescriptor>
                <PortDescriptor>
                    <ProgramName>sunwebadmin</ProgramName>
                    <Port>8800</Port>
                </PortDescriptor>
                <PortDescriptor>
                    <ProgramName>unknown</ProgramName>
                    <Port>16018</Port>
                </PortDescriptor>
            </PortsDescriptor>
        </AdversarySystemDescriptor>
        <ReverseIPDescriptor AmountOfVirtualHosts="0"/>
    </IPDescriptor>
    <DateDescriptor>
        <Fulldate>2015-09-14</Fulldate>
        <Year>2015</Year>
        <Month>09</Month>
        <Day>14</Day>
        <Time>14:14:07</Time>
    </DateDescriptor>
</Attack>
