<?xml version="1.0" encoding="UTF-8" standalone="yes"?>
<Attack>
    <IPDescriptor>
        <IPAddress>61.164.83.34</IPAddress>
        <LocationDescriptor>
            <CountryName>China</CountryName>
            <CountryCode>CN</CountryCode>
            <RegionName>Zhejiang Sheng</RegionName>
            <RegionCode>33</RegionCode>
            <City>Ningbo</City>
            <ZipCode></ZipCode>
            <TimeZone>Asia/Shanghai</TimeZone>
            <Latitude>29.8782</Latitude>
            <Longitude>121.5495</Longitude>
            <MetroCode>0</MetroCode>
        </LocationDescriptor>
        <BlacklistingDescriptor>
            <BlacklistingLevel>3</BlacklistingLevel>
        </BlacklistingDescriptor>
        <AdversaryHostDescriptor>
            <NetworkRange>61.0.0.0 - 61.255.255.255</NetworkRange>
            <NetworkSize>16777215</NetworkSize>
            <NetworkName>IPv4 address block not managed by the RIPE NCC</NetworkName>
        </AdversaryHostDescriptor>
        <AdversarySystemDescriptor>
            <OSDescriptor>OpenWrt Kamikaze 7.09 (Linux 2.6.22)</OSDescriptor>
            <PortsDescriptor amount="11">
                <PortDescriptor>
                    <ProgramName>ssh</ProgramName>
                    <Port>22</Port>
                </PortDescriptor>
                <PortDescriptor>
                    <ProgramName>telnet</ProgramName>
                    <Port>23</Port>
                </PortDescriptor>
                <PortDescriptor>
                    <ProgramName>http</ProgramName>
                    <Port>80</Port>
                </PortDescriptor>
                <PortDescriptor>
                    <ProgramName>microsoft-ds</ProgramName>
                    <Port>445</Port>
                </PortDescriptor>
                <PortDescriptor>
                    <ProgramName>rtsp</ProgramName>
                    <Port>554</Port>
                </PortDescriptor>
                <PortDescriptor>
                    <ProgramName>mysql</ProgramName>
                    <Port>3306</Port>
                </PortDescriptor>
                <PortDescriptor>
                    <ProgramName>krb524</ProgramName>
                    <Port>4444</Port>
                </PortDescriptor>
                <PortDescriptor>
                    <ProgramName>afs3-callback</ProgramName>
                    <Port>7001</Port>
                </PortDescriptor>
                <PortDescriptor>
                    <ProgramName>http-alt</ProgramName>
                    <Port>8000</Port>
                </PortDescriptor>
                <PortDescriptor>
                    <ProgramName>trivnet1</ProgramName>
                    <Port>8200</Port>
                </PortDescriptor>
                <PortDescriptor>
                    <ProgramName>sun-answerbook</ProgramName>
                    <Port>8888</Port>
                </PortDescriptor>
            </PortsDescriptor>
        </AdversarySystemDescriptor>
        <ReverseIPDescriptor AmountOfVirtualHosts="0"/>
    </IPDescriptor>
    <DateDescriptor>
        <Fulldate>2015-04-19</Fulldate>
        <Year>2015</Year>
        <Month>04</Month>
        <Day>19</Day>
        <Time>10:40:04</Time>
    </DateDescriptor>
</Attack>
