<?xml version="1.0" encoding="UTF-8" standalone="yes"?>
<Attack>
    <IPDescriptor>
        <IPAddress>72.249.118.47</IPAddress>
        <LocationDescriptor>
            <CountryName>United States</CountryName>
            <CountryCode>US</CountryCode>
            <RegionName>Missouri</RegionName>
            <RegionCode>MO</RegionCode>
            <City>St Louis</City>
            <ZipCode>63131</ZipCode>
            <TimeZone>America/Chicago</TimeZone>
            <Latitude>38.6143</Latitude>
            <Longitude>-90.4444</Longitude>
            <MetroCode>609</MetroCode>
        </LocationDescriptor>
        <BlacklistingDescriptor>
            <BlacklistingLevel>3</BlacklistingLevel>
        </BlacklistingDescriptor>
        <AdversaryHostDescriptor>
            <NetworkRange>72.0.0.0 - 72.255.255.255</NetworkRange>
            <NetworkSize>16777215</NetworkSize>
            <NetworkName>IPv4 address block not managed by the RIPE NCC</NetworkName>
        </AdversaryHostDescriptor>
        <AdversarySystemDescriptor>
            <PortsDescriptor amount="0"/>
        </AdversarySystemDescriptor>
        <ReverseIPDescriptor AmountOfVirtualHosts="12">
            <VirtualHost>
                <VirtualHostname>andrewbuzzell.ca</VirtualHostname>
            </VirtualHost>
            <VirtualHost>
                <VirtualHostname>gbecker.ca</VirtualHostname>
            </VirtualHost>
            <VirtualHost>
                <VirtualHostname>imagemark.ca</VirtualHostname>
            </VirtualHost>
            <VirtualHost>
                <VirtualHostname>localgrouprides.com</VirtualHostname>
            </VirtualHost>
            <VirtualHost>
                <VirtualHostname>netplex.ca</VirtualHostname>
            </VirtualHost>
            <VirtualHost>
                <VirtualHostname>nonprofitnet.ca</VirtualHostname>
            </VirtualHost>
            <VirtualHost>
                <VirtualHostname>ns1.web1.netplex.ca</VirtualHostname>
            </VirtualHost>
            <VirtualHost>
                <VirtualHostname>pxi.ca</VirtualHostname>
            </VirtualHost>
            <VirtualHost>
                <VirtualHostname>stopanimalabuse.ca</VirtualHostname>
            </VirtualHost>
            <VirtualHost>
                <VirtualHostname>umva.ca</VirtualHostname>
            </VirtualHost>
            <VirtualHost>
                <VirtualHostname>web1.netplex.ca</VirtualHostname>
            </VirtualHost>
            <VirtualHost>
                <VirtualHostname>whiterabbitarts.ca</VirtualHostname>
            </VirtualHost>
        </ReverseIPDescriptor>
    </IPDescriptor>
    <DateDescriptor>
        <Fulldate>2015-11-02</Fulldate>
        <Year>2015</Year>
        <Month>11</Month>
        <Day>02</Day>
        <Time>05:13:39</Time>
    </DateDescriptor>
</Attack>
