<?xml version="1.0" encoding="UTF-8" standalone="yes"?>
<Attack>
    <IPDescriptor>
        <IPAddress>60.169.78.38</IPAddress>
        <LocationDescriptor>
            <CountryName>China</CountryName>
            <CountryCode>CN</CountryCode>
            <RegionName>Anhui Sheng</RegionName>
            <RegionCode>34</RegionCode>
            <City>Hefei</City>
            <ZipCode></ZipCode>
            <TimeZone>Asia/Shanghai</TimeZone>
            <Latitude>31.8639</Latitude>
            <Longitude>117.2808</Longitude>
            <MetroCode>0</MetroCode>
        </LocationDescriptor>
        <BlacklistingDescriptor>
            <BlacklistingLevel>5</BlacklistingLevel>
        </BlacklistingDescriptor>
        <AdversaryHostDescriptor>
            <NetworkRange>60.0.0.0 - 60.255.255.255</NetworkRange>
            <NetworkSize>16777215</NetworkSize>
            <NetworkName>IPv4 address block not managed by the RIPE NCC</NetworkName>
        </AdversaryHostDescriptor>
        <AdversarySystemDescriptor>
            <OSDescriptor>Linux 2.6.39</OSDescriptor>
            <PortsDescriptor amount="24">
                <PortDescriptor>
                    <ProgramName>ssh</ProgramName>
                    <Port>22</Port>
                </PortDescriptor>
                <PortDescriptor>
                    <ProgramName>nameserver</ProgramName>
                    <Port>42</Port>
                </PortDescriptor>
                <PortDescriptor>
                    <ProgramName>http</ProgramName>
                    <Port>80</Port>
                </PortDescriptor>
                <PortDescriptor>
                    <ProgramName>msrpc</ProgramName>
                    <Port>135</Port>
                </PortDescriptor>
                <PortDescriptor>
                    <ProgramName>netbios-ssn</ProgramName>
                    <Port>139</Port>
                </PortDescriptor>
                <PortDescriptor>
                    <ProgramName>https</ProgramName>
                    <Port>443</Port>
                </PortDescriptor>
                <PortDescriptor>
                    <ProgramName>microsoft-ds</ProgramName>
                    <Port>445</Port>
                </PortDescriptor>
                <PortDescriptor>
                    <ProgramName>http-rpc-epmap</ProgramName>
                    <Port>593</Port>
                </PortDescriptor>
                <PortDescriptor>
                    <ProgramName>NFS-or-IIS</ProgramName>
                    <Port>1025</Port>
                </PortDescriptor>
                <PortDescriptor>
                    <ProgramName>instl_bootc</ProgramName>
                    <Port>1068</Port>
                </PortDescriptor>
                <PortDescriptor>
                    <ProgramName>ms-sql-m</ProgramName>
                    <Port>1434</Port>
                </PortDescriptor>
                <PortDescriptor>
                    <ProgramName>mps-raft</ProgramName>
                    <Port>1700</Port>
                </PortDescriptor>
                <PortDescriptor>
                    <ProgramName>fj-hdnet</ProgramName>
                    <Port>1717</Port>
                </PortDescriptor>
                <PortDescriptor>
                    <ProgramName>h323gatedisc</ProgramName>
                    <Port>1718</Port>
                </PortDescriptor>
                <PortDescriptor>
                    <ProgramName>h323gatestat</ProgramName>
                    <Port>1719</Port>
                </PortDescriptor>
                <PortDescriptor>
                    <ProgramName>H.323/Q.931</ProgramName>
                    <Port>1720</Port>
                </PortDescriptor>
                <PortDescriptor>
                    <ProgramName>caicci</ProgramName>
                    <Port>1721</Port>
                </PortDescriptor>
                <PortDescriptor>
                    <ProgramName>pptp</ProgramName>
                    <Port>1723</Port>
                </PortDescriptor>
                <PortDescriptor>
                    <ProgramName>squid-http</ProgramName>
                    <Port>3128</Port>
                </PortDescriptor>
                <PortDescriptor>
                    <ProgramName>mysql</ProgramName>
                    <Port>3306</Port>
                </PortDescriptor>
                <PortDescriptor>
                    <ProgramName>krb524</ProgramName>
                    <Port>4444</Port>
                </PortDescriptor>
                <PortDescriptor>
                    <ProgramName>irc</ProgramName>
                    <Port>6669</Port>
                </PortDescriptor>
                <PortDescriptor>
                    <ProgramName>http-alt</ProgramName>
                    <Port>8000</Port>
                </PortDescriptor>
                <PortDescriptor>
                    <ProgramName>http-proxy</ProgramName>
                    <Port>8080</Port>
                </PortDescriptor>
            </PortsDescriptor>
        </AdversarySystemDescriptor>
        <ReverseIPDescriptor AmountOfVirtualHosts="0"/>
    </IPDescriptor>
    <DateDescriptor>
        <Fulldate>2015-12-21</Fulldate>
        <Year>2015</Year>
        <Month>12</Month>
        <Day>21</Day>
        <Time>01:19:45</Time>
    </DateDescriptor>
</Attack>
