<?xml version="1.0" encoding="UTF-8" standalone="yes"?>
<Attack>
    <IPDescriptor>
        <IPAddress>80.82.78.164</IPAddress>
        <LocationDescriptor>
            <CountryName>Netherlands</CountryName>
            <CountryCode>NL</CountryCode>
            <RegionName></RegionName>
            <RegionCode></RegionCode>
            <City></City>
            <ZipCode></ZipCode>
            <TimeZone>Europe/Amsterdam</TimeZone>
            <Latitude>52.3667</Latitude>
            <Longitude>4.9</Longitude>
            <MetroCode>0</MetroCode>
        </LocationDescriptor>
        <BlacklistingDescriptor>
            <BlacklistingLevel>8</BlacklistingLevel>
        </BlacklistingDescriptor>
        <AdversaryHostDescriptor>
            <NetworkRange>80.82.64.0 - 80.82.79.255</NetworkRange>
            <NetworkSize>4095</NetworkSize>
            <NetworkName>Ecatel LTD</NetworkName>
        </AdversaryHostDescriptor>
        <AdversarySystemDescriptor>
            <OSDescriptor>OpenWrt 12.09-rc1 Attitude Adjustment (Linux 3.3 - 3.7)</OSDescriptor>
            <PortsDescriptor amount="3">
                <PortDescriptor>
                    <ProgramName>ssh</ProgramName>
                    <Port>22</Port>
                </PortDescriptor>
                <PortDescriptor>
                    <ProgramName>http</ProgramName>
                    <Port>80</Port>
                </PortDescriptor>
                <PortDescriptor>
                    <ProgramName>nrpe</ProgramName>
                    <Port>5666</Port>
                </PortDescriptor>
            </PortsDescriptor>
        </AdversarySystemDescriptor>
        <ReverseIPDescriptor AmountOfVirtualHosts="0"/>
    </IPDescriptor>
    <DateDescriptor>
        <Fulldate>2015-07-19</Fulldate>
        <Year>2015</Year>
        <Month>07</Month>
        <Day>19</Day>
        <Time>21:18:28</Time>
    </DateDescriptor>
</Attack>
