<?xml version="1.0" encoding="UTF-8" standalone="yes"?>
<Attack>
    <IPDescriptor>
        <IPAddress>42.202.146.65</IPAddress>
        <LocationDescriptor>
            <CountryName>China</CountryName>
            <CountryCode>CN</CountryCode>
            <RegionName>Liaoning</RegionName>
            <RegionCode>21</RegionCode>
            <City>Shenyang</City>
            <ZipCode></ZipCode>
            <TimeZone>Asia/Shanghai</TimeZone>
            <Latitude>41.7922</Latitude>
            <Longitude>123.4328</Longitude>
            <MetroCode>0</MetroCode>
        </LocationDescriptor>
        <BlacklistingDescriptor>
            <BlacklistingLevel>4</BlacklistingLevel>
        </BlacklistingDescriptor>
        <AdversaryHostDescriptor>
            <NetworkRange>42.0.0.0 - 42.255.255.255</NetworkRange>
            <NetworkSize>16777215</NetworkSize>
            <NetworkName>IPv4 address block not managed by the RIPE NCC</NetworkName>
        </AdversaryHostDescriptor>
        <AdversarySystemDescriptor>
            <OSDescriptor>OpenWrt White Russian 0.9 (Linux 2.4.30)</OSDescriptor>
            <PortsDescriptor amount="17">
                <PortDescriptor>
                    <ProgramName>ftp</ProgramName>
                    <Port>21</Port>
                </PortDescriptor>
                <PortDescriptor>
                    <ProgramName>http</ProgramName>
                    <Port>80</Port>
                </PortDescriptor>
                <PortDescriptor>
                    <ProgramName>rpcbind</ProgramName>
                    <Port>111</Port>
                </PortDescriptor>
                <PortDescriptor>
                    <ProgramName>microsoft-ds</ProgramName>
                    <Port>445</Port>
                </PortDescriptor>
                <PortDescriptor>
                    <ProgramName>down</ProgramName>
                    <Port>2022</Port>
                </PortDescriptor>
                <PortDescriptor>
                    <ProgramName>mysql</ProgramName>
                    <Port>3306</Port>
                </PortDescriptor>
                <PortDescriptor>
                    <ProgramName>afs3-fileserver</ProgramName>
                    <Port>7000</Port>
                </PortDescriptor>
                <PortDescriptor>
                    <ProgramName>afs3-callback</ProgramName>
                    <Port>7001</Port>
                </PortDescriptor>
                <PortDescriptor>
                    <ProgramName>ajp13</ProgramName>
                    <Port>8009</Port>
                </PortDescriptor>
                <PortDescriptor>
                    <ProgramName>http-proxy</ProgramName>
                    <Port>8080</Port>
                </PortDescriptor>
                <PortDescriptor>
                    <ProgramName>xprint-server</ProgramName>
                    <Port>8100</Port>
                </PortDescriptor>
                <PortDescriptor>
                    <ProgramName>trivnet1</ProgramName>
                    <Port>8200</Port>
                </PortDescriptor>
                <PortDescriptor>
                    <ProgramName>cvd</ProgramName>
                    <Port>8400</Port>
                </PortDescriptor>
                <PortDescriptor>
                    <ProgramName>abarsd</ProgramName>
                    <Port>8402</Port>
                </PortDescriptor>
                <PortDescriptor>
                    <ProgramName>fmtp</ProgramName>
                    <Port>8500</Port>
                </PortDescriptor>
                <PortDescriptor>
                    <ProgramName>asterix</ProgramName>
                    <Port>8600</Port>
                </PortDescriptor>
                <PortDescriptor>
                    <ProgramName>unknown</ProgramName>
                    <Port>55555</Port>
                </PortDescriptor>
            </PortsDescriptor>
        </AdversarySystemDescriptor>
        <ReverseIPDescriptor AmountOfVirtualHosts="0"/>
    </IPDescriptor>
    <DateDescriptor>
        <Fulldate>2015-07-06</Fulldate>
        <Year>2015</Year>
        <Month>07</Month>
        <Day>06</Day>
        <Time>15:30:32</Time>
    </DateDescriptor>
</Attack>
