<?xml version="1.0" encoding="UTF-8" standalone="yes"?>
<Attack>
    <IPDescriptor>
        <IPAddress>50.61.233.106</IPAddress>
        <LocationDescriptor>
            <CountryName>United States</CountryName>
            <CountryCode>US</CountryCode>
            <RegionName>New Jersey</RegionName>
            <RegionCode>NJ</RegionCode>
            <City>Secaucus</City>
            <ZipCode>07094</ZipCode>
            <TimeZone>America/New_York</TimeZone>
            <Latitude>40.7801</Latitude>
            <Longitude>-74.0633</Longitude>
            <MetroCode>501</MetroCode>
        </LocationDescriptor>
        <BlacklistingDescriptor>
            <BlacklistingLevel>3</BlacklistingLevel>
        </BlacklistingDescriptor>
        <AdversaryHostDescriptor>
            <NetworkRange>50.0.0.0 - 50.255.255.255</NetworkRange>
            <NetworkSize>16777215</NetworkSize>
            <NetworkName>IPv4 address block not managed by the RIPE NCC</NetworkName>
        </AdversaryHostDescriptor>
        <AdversarySystemDescriptor>
            <OSDescriptor></OSDescriptor>
            <PortsDescriptor amount="33">
                <PortDescriptor>
                    <ProgramName>ftp-data</ProgramName>
                    <Port>20</Port>
                </PortDescriptor>
                <PortDescriptor>
                    <ProgramName>ftp</ProgramName>
                    <Port>21</Port>
                </PortDescriptor>
                <PortDescriptor>
                    <ProgramName>ssh</ProgramName>
                    <Port>22</Port>
                </PortDescriptor>
                <PortDescriptor>
                    <ProgramName>smtp</ProgramName>
                    <Port>25</Port>
                </PortDescriptor>
                <PortDescriptor>
                    <ProgramName>domain</ProgramName>
                    <Port>53</Port>
                </PortDescriptor>
                <PortDescriptor>
                    <ProgramName>http</ProgramName>
                    <Port>80</Port>
                </PortDescriptor>
                <PortDescriptor>
                    <ProgramName>pop3</ProgramName>
                    <Port>110</Port>
                </PortDescriptor>
                <PortDescriptor>
                    <ProgramName>imap</ProgramName>
                    <Port>143</Port>
                </PortDescriptor>
                <PortDescriptor>
                    <ProgramName>https</ProgramName>
                    <Port>443</Port>
                </PortDescriptor>
                <PortDescriptor>
                    <ProgramName>smtps</ProgramName>
                    <Port>465</Port>
                </PortDescriptor>
                <PortDescriptor>
                    <ProgramName>submission</ProgramName>
                    <Port>587</Port>
                </PortDescriptor>
                <PortDescriptor>
                    <ProgramName>imaps</ProgramName>
                    <Port>993</Port>
                </PortDescriptor>
                <PortDescriptor>
                    <ProgramName>pop3s</ProgramName>
                    <Port>995</Port>
                </PortDescriptor>
                <PortDescriptor>
                    <ProgramName>ppp</ProgramName>
                    <Port>3000</Port>
                </PortDescriptor>
                <PortDescriptor>
                    <ProgramName>cgms</ProgramName>
                    <Port>3003</Port>
                </PortDescriptor>
                <PortDescriptor>
                    <ProgramName>deslogind</ProgramName>
                    <Port>3006</Port>
                </PortDescriptor>
                <PortDescriptor>
                    <ProgramName>event_listener</ProgramName>
                    <Port>3017</Port>
                </PortDescriptor>
                <PortDescriptor>
                    <ProgramName>arepa-cas</ProgramName>
                    <Port>3030</Port>
                </PortDescriptor>
                <PortDescriptor>
                    <ProgramName>eppc</ProgramName>
                    <Port>3031</Port>
                </PortDescriptor>
                <PortDescriptor>
                    <ProgramName>powerchute</ProgramName>
                    <Port>3052</Port>
                </PortDescriptor>
                <PortDescriptor>
                    <ProgramName>poweronnud</ProgramName>
                    <Port>3168</Port>
                </PortDescriptor>
                <PortDescriptor>
                    <ProgramName>xnm-clear-text</ProgramName>
                    <Port>3221</Port>
                </PortDescriptor>
                <PortDescriptor>
                    <ProgramName>winshadow</ProgramName>
                    <Port>3261</Port>
                </PortDescriptor>
                <PortDescriptor>
                    <ProgramName>unknown</ProgramName>
                    <Port>3300</Port>
                </PortDescriptor>
                <PortDescriptor>
                    <ProgramName>unknown</ProgramName>
                    <Port>3301</Port>
                </PortDescriptor>
                <PortDescriptor>
                    <ProgramName>mysql</ProgramName>
                    <Port>3306</Port>
                </PortDescriptor>
                <PortDescriptor>
                    <ProgramName>active-net</ProgramName>
                    <Port>3323</Port>
                </PortDescriptor>
                <PortDescriptor>
                    <ProgramName>active-net</ProgramName>
                    <Port>3324</Port>
                </PortDescriptor>
                <PortDescriptor>
                    <ProgramName>active-net</ProgramName>
                    <Port>3325</Port>
                </PortDescriptor>
                <PortDescriptor>
                    <ProgramName>dec-notes</ProgramName>
                    <Port>3333</Port>
                </PortDescriptor>
                <PortDescriptor>
                    <ProgramName>msdtc</ProgramName>
                    <Port>3372</Port>
                </PortDescriptor>
                <PortDescriptor>
                    <ProgramName>ms-wbt-server</ProgramName>
                    <Port>3389</Port>
                </PortDescriptor>
                <PortDescriptor>
                    <ProgramName>dsc</ProgramName>
                    <Port>3390</Port>
                </PortDescriptor>
            </PortsDescriptor>
        </AdversarySystemDescriptor>
        <ReverseIPDescriptor AmountOfVirtualHosts="1">
            <VirtualHost>
                <VirtualHostname>syspodv1.arvixevps.com</VirtualHostname>
            </VirtualHost>
        </ReverseIPDescriptor>
    </IPDescriptor>
    <DateDescriptor>
        <Fulldate>2015-07-19</Fulldate>
        <Year>2015</Year>
        <Month>07</Month>
        <Day>19</Day>
        <Time>07:27:25</Time>
    </DateDescriptor>
</Attack>
